histoencoder/__init__.py
histoencoder/_cli/__init__.py
histoencoder/_cli/_cluster.py
histoencoder/_cli/_extract.py
histoencoder/_cli/_run.py
histoencoder/_cli/_utils.py
histoencoder/functional/__init__.py
histoencoder/functional/_check.py
histoencoder/functional/_cluster.py
histoencoder/functional/_features.py
histoencoder/functional/_freeze.py
histoencoder/functional/_model.py
histoencoder/functional/_params.py
histoencoder/functional/_writer.py
histoencoder-0.1.1.dist-info/METADATA
histoencoder-0.1.1.dist-info/WHEEL
histoencoder-0.1.1.dist-info/entry_points.txt
histoencoder-0.1.1.dist-info/RECORD
