Metadata-Version: 2.1
Name: histoencoder
Version: 0.1.1
Summary: Foundation models for digital pathology.
Author: jopo666
Author-email: jopo@birdlover.com
Requires-Python: >=3.9,<4.0
Classifier: Programming Language :: Python :: 3
Classifier: Programming Language :: Python :: 3.9
Classifier: Programming Language :: Python :: 3.10
Classifier: Programming Language :: Python :: 3.11
Requires-Dist: histoprep (>=2,<3)
Requires-Dist: rich-click (>=1.6,<2.0)
Requires-Dist: scikit-learn (>=1.2,<2.0)
Requires-Dist: timm (>=0.5,<0.6)
Requires-Dist: torch (>=2,<3)
Requires-Dist: torchvision (>=0.15,<0.16)
